Metadata-Version: 2.4
Name: devhub-cms-mcp
Version: 0.3.0
Summary: DevHub CMS LLM integration through the Model Context Protocol
Requires-Python: >=3.10
Requires-Dist: mcp[cli]>=1.4.1
Requires-Dist: requests-oauthlib>=2.0.0
Provides-Extra: test
Requires-Dist: pytest>=7.0.0; extra == "test"
Requires-Dist: pytest-mock>=3.10.0; extra == "test"
Requires-Dist: pytest-cov>=4.1.0; extra == "test"
